{
  "annotations": {
    "list": [
      {
        "builtIn": 1,
        "datasource": {
          "type": "grafana",
          "uid": "-- Grafana --"
        },
        "enable": true,
        "hide": true,
        "iconColor": "rgba(0, 211, 255, 1)",
        "name": "Annotations & Alerts",
        "type": "dashboard"
      }
    ]
  },
  "editable": true,
  "fiscalYearStartMonth": 0,
  "graphTooltip": 0,
  "id": null,
  "links": [],
  "panels": [
    {
      "datasource": {
        "type": "prometheus",
        "uid": "prometheus"
      },
      "fieldConfig": {
        "defaults": {
          "color": {
            "mode": "palette-classic"
          },
          "mappings": [],
          "unit": "short"
        },
        "overrides": []
      },
      "gridPos": {
        "h": 8,
        "w": 12,
        "x": 0,
        "y": 0
      },
      "id": 1,
      "options": {
        "legend": {
          "displayMode": "table",
          "placement": "bottom",
          "showLegend": true
        },
        "tooltip": {
          "mode": "multi",
          "sort": "desc"
        }
      },
      "targets": [
        {
          "editorMode": "code",
          "expr": "scrape_samples_scraped",
          "legendFormat": "{{job}}",
          "range": true,
          "refId": "A"
        }
      ],
      "title": "Scraped Samples by Job",
      "type": "timeseries"
    },
    {
      "datasource": {
        "type": "prometheus",
        "uid": "prometheus"
      },
      "fieldConfig": {
        "defaults": {
          "color": {
            "mode": "palette-classic"
          },
          "custom": {
            "drawStyle": "line",
            "fillOpacity": 15,
            "lineInterpolation": "linear",
            "lineWidth": 2,
            "showPoints": "never"
          },
          "unit": "s"
        },
        "overrides": []
      },
      "gridPos": {
        "h": 8,
        "w": 12,
        "x": 12,
        "y": 0
      },
      "id": 2,
      "options": {
        "legend": {
          "displayMode": "table",
          "placement": "bottom",
          "showLegend": true
        },
        "tooltip": {
          "mode": "multi",
          "sort": "desc"
        }
      },
      "targets": [
        {
          "editorMode": "code",
          "expr": "scrape_duration_seconds",
          "legendFormat": "{{job}}",
          "range": true,
          "refId": "A"
        }
      ],
      "title": "Scrape Duration",
      "type": "timeseries"
    },
    {
      "datasource": {
        "type": "prometheus",
        "uid": "prometheus"
      },
      "fieldConfig": {
        "defaults": {
          "color": {
            "mode": "palette-classic"
          },
          "custom": {
            "align": "auto",
            "cellOptions": {
              "type": "auto"
            },
            "inspect": false
          },
          "mappings": [],
          "unit": "short"
        },
        "overrides": []
      },
      "gridPos": {
        "h": 8,
        "w": 10,
        "x": 0,
        "y": 8
      },
      "id": 3,
      "options": {
        "cellHeight": "sm",
        "footer": {
          "show": false
        },
        "showHeader": true
      },
      "targets": [
        {
          "editorMode": "code",
          "expr": "up{job=~\"prometheus|loki|node_exporter|dcgm_exporter\"}",
          "format": "table",
          "instant": true,
          "legendFormat": "{{job}}",
          "refId": "A"
        }
      ],
      "title": "Target Status Table",
      "transformations": [
        {
          "id": "organize",
          "options": {
            "excludeByName": {
              "__name__": true,
              "Time": true
            },
            "renameByName": {
              "Value": "up"
            }
          }
        }
      ],
      "type": "table"
    },
    {
      "datasource": {
        "type": "loki",
        "uid": "loki"
      },
      "gridPos": {
        "h": 8,
        "w": 14,
        "x": 10,
        "y": 8
      },
      "id": 4,
      "options": {
        "dedupStrategy": "none",
        "enableLogDetails": true,
        "prettifyLogMessage": false,
        "showCommonLabels": false,
        "showLabels": true,
        "showTime": true,
        "sortOrder": "Descending",
        "wrapLogMessage": true
      },
      "targets": [
        {
          "expr": "{container_name=~\"aivn-.*|churn-prediction-.*|node_exporter|dcgm-exporter\"}",
          "queryType": "range",
          "refId": "A"
        }
      ],
      "title": "Recent Container Logs",
      "type": "logs"
    }
  ],
  "refresh": "10s",
  "schemaVersion": 39,
  "style": "dark",
  "tags": [
    "mlops",
    "prometheus",
    "loki"
  ],
  "templating": {
    "list": []
  },
  "time": {
    "from": "now-1h",
    "to": "now"
  },
  "timepicker": {},
  "timezone": "",
  "title": "MLOps Observability Overview",
  "uid": "mlops-observability-overview",
  "version": 1,
  "weekStart": ""
}
